{
  "ip_addresses": [],
  "aliases": [],
  "acronyms": [
    "WXSTC"
  ],
  "links": [
    "https://www.wxstc.cn"
  ],
  "country": {
    "country_name": "China",
    "country_code": "CN"
  },
  "name": "Wuxi Vocational College of Science and Technology",
  "wikipedia_url": "https://zh.m.wikipedia.org/zh-hans/%E6%97%A0%E9%94%A1%E7%A7%91%E6%8A%80%E8%81%8C%E4%B8%9A%E5%AD%A6%E9%99%A2",
  "addresses": [
    {
      "lat": 31.56887,
      "lng": 120.28857,
      "state": null,
      "state_code": null,
      "country_geonames_id": 1814991,
      "city": "Wuxi",
      "geonames_city": {
        "id": 1790923,
        "city": "Wuxi",
        "geonames_admin1": {
          "name": "Jiangsu",
          "ascii_name": "Jiangsu",
          "id": 1806260,
          "code": "CN.04"
        },
        "geonames_admin2": {
          "name": "Wuxi Shi",
          "id": 1790902,
          "ascii_name": "Wuxi Shi",
          "code": "CN.04.3202"
        },
        "nuts_level1": {
          "name": null,
          "code": null
        },
        "nuts_level2": {
          "name": null,
          "code": null
        },
        "nuts_level3": {
          "name": null,
          "code": null
        },
        "license": {
          "attribution": "Data from geonames.org under a CC-BY 3.0 license",
          "license": "http://creativecommons.org/licenses/by/3.0/"
        }
      },
      "primary": false,
      "postcode": null,
      "line": null
    }
  ],
  "types": [
    "Education"
  ],
  "external_ids": {
    "Wikidata": {
      "preferred": "Q11085981",
      "all": [
        "Q11085981"
      ]
    }
  },
  "established": 2003,
  "relationships": [],
  "email_address": null,
  "id": "https://ror.org/00y0p0f23",
  "labels": [
    {
      "label": "无锡科技职业学院",
      "iso639": "zh"
    }
  ],
  "status": "active"
}