{
  "admin": {
    "created": {
      "date": "2026-05-04",
      "schema_version": "2.1"
    },
    "last_modified": {
      "date": "2026-05-05",
      "schema_version": "2.1"
    }
  },
  "domains": [
    "mzmarketing.org"
  ],
  "established": null,
  "external_ids": [],
  "id": "https://ror.org/01q3zq576",
  "links": [
    {
      "type": "website",
      "value": "https://mzmarketing.org"
    }
  ],
  "locations": [
    {
      "geonames_details": {
        "continent_code": "EU",
        "continent_name": "Europe",
        "country_code": "MK",
        "country_name": "North Macedonia",
        "country_subdivision_code": null,
        "country_subdivision_name": "Grad Skopje",
        "lat": 41.99646,
        "lng": 21.43141,
        "name": "Skopje"
      },
      "geonames_id": 785842
    }
  ],
  "names": [
    {
      "lang": "en",
      "types": [
        "label",
        "ror_display"
      ],
      "value": "Macedonian Marketing Association Marketing – Skopje"
    }
  ],
  "relationships": [],
  "status": "active",
  "types": [
    "other"
  ]
}