{
  "admin": {
    "created": {
      "date": "2026-05-30",
      "schema_version": "2.1"
    },
    "last_modified": {
      "date": "2026-06-02",
      "schema_version": "2.1"
    }
  },
  "domains": [
    "3skin.no"
  ],
  "established": null,
  "external_ids": [],
  "id": "https://ror.org/015pamw03",
  "links": [
    {
      "type": "website",
      "value": "https://www.3skin.no"
    }
  ],
  "locations": [
    {
      "geonames_details": {
        "continent_code": "EU",
        "continent_name": "Europe",
        "country_code": "NO",
        "country_name": "Norway",
        "country_subdivision_code": "03",
        "country_subdivision_name": "Oslo",
        "lat": 59.91273,
        "lng": 10.74609,
        "name": "Oslo"
      },
      "geonames_id": 3143244
    }
  ],
  "names": [
    {
      "lang": null,
      "types": [
        "acronym"
      ],
      "value": "3SKIN"
    },
    {
      "lang": null,
      "types": [
        "label"
      ],
      "value": "3SKIN AS"
    },
    {
      "lang": null,
      "types": [
        "label",
        "ror_display"
      ],
      "value": "3SKIN AS (Norway)"
    },
    {
      "lang": null,
      "types": [
        "alias"
      ],
      "value": "3Skin"
    }
  ],
  "relationships": [],
  "status": "active",
  "types": [
    "company"
  ]
}