{
  "admin": {
    "created": {
      "date": "2018-11-14",
      "schema_version": "1.0"
    },
    "last_modified": {
      "date": "2024-10-21",
      "schema_version": "2.0"
    }
  },
  "domains": [
    "izs.it"
  ],
  "established": 1941,
  "external_ids": [
    {
      "all": [
        "grid.419578.6"
      ],
      "preferred": "grid.419578.6",
      "type": "grid"
    },
    {
      "all": [
        "0000 0004 1805 1770"
      ],
      "preferred": null,
      "type": "isni"
    }
  ],
  "id": "https://ror.org/04es49j42",
  "links": [
    {
      "type": "website",
      "value": "https://www.izs.it"
    }
  ],
  "locations": [
    {
      "geonames_details": {
        "country_code": "IT",
        "country_name": "Italy",
        "lat": 42.66123,
        "lng": 13.69901,
        "name": "Teramo"
      },
      "geonames_id": 3165803
    }
  ],
  "names": [
    {
      "lang": null,
      "types": [
        "acronym"
      ],
      "value": "IZSAM"
    },
    {
      "lang": "it",
      "types": [
        "ror_display",
        "label"
      ],
      "value": "Istituto Zooprofilattico Sperimentale dell'Abruzzo e del Molise G. Caporale"
    }
  ],
  "relationships": [],
  "status": "active",
  "types": [
    "facility"
  ]
}