{
  "admin": {
    "created": {
      "date": "2023-09-14",
      "schema_version": "1.0"
    },
    "last_modified": {
      "date": "2025-06-24",
      "schema_version": "2.1"
    }
  },
  "domains": [],
  "established": 2019,
  "external_ids": [
    {
      "all": [
        "0000 0005 1103 721X"
      ],
      "preferred": "0000 0005 1103 721X",
      "type": "isni"
    }
  ],
  "id": "https://ror.org/02hrx0m28",
  "links": [
    {
      "type": "website",
      "value": "https://www.tudelft.nl/library/openpublishing"
    }
  ],
  "locations": [
    {
      "geonames_details": {
        "continent_code": "EU",
        "continent_name": "Europe",
        "country_code": "NL",
        "country_name": "The Netherlands",
        "country_subdivision_code": "ZH",
        "country_subdivision_name": "South Holland",
        "lat": 52.00667,
        "lng": 4.35556,
        "name": "Delft"
      },
      "geonames_id": 2757345
    }
  ],
  "names": [
    {
      "lang": "en",
      "types": [
        "alias"
      ],
      "value": "TU Delft OPEN"
    },
    {
      "lang": "en",
      "types": [
        "ror_display",
        "label"
      ],
      "value": "TU Delft OPEN Publishing"
    }
  ],
  "relationships": [
    {
      "label": "Delft University of Technology",
      "type": "parent",
      "id": "https://ror.org/02e2c7k09"
    }
  ],
  "status": "active",
  "types": [
    "other"
  ]
}