{
  "admin": {
    "created": {
      "date": "2018-11-14",
      "schema_version": "1.0"
    },
    "last_modified": {
      "date": "2026-01-29",
      "schema_version": "2.1"
    }
  },
  "domains": [
    "scivp.lviv.ua"
  ],
  "established": 1991,
  "external_ids": [
    {
      "all": [
        "grid.495190.0"
      ],
      "preferred": "grid.495190.0",
      "type": "grid"
    }
  ],
  "id": "https://ror.org/03cb4jc22",
  "links": [
    {
      "type": "website",
      "value": "https://www.scivp.lviv.ua"
    }
  ],
  "locations": [
    {
      "geonames_details": {
        "continent_code": "EU",
        "continent_name": "Europe",
        "country_code": "UA",
        "country_name": "Ukraine",
        "country_subdivision_code": "46",
        "country_subdivision_name": "Lviv",
        "lat": 49.83826,
        "lng": 24.02324,
        "name": "Lviv"
      },
      "geonames_id": 702550
    }
  ],
  "names": [
    {
      "lang": null,
      "types": [
        "acronym"
      ],
      "value": "DNDKI"
    },
    {
      "lang": "en",
      "types": [
        "ror_display",
        "label"
      ],
      "value": "SCIVP of Veterinary Medicinal Products and Feed Additives"
    },
    {
      "lang": "en",
      "types": [
        "alias"
      ],
      "value": "State Scientific-Research Control Institute of Veterinary Preparations and Feed Additives"
    },
    {
      "lang": null,
      "types": [
        "acronym"
      ],
      "value": "ДНДКІ"
    },
    {
      "lang": "uk",
      "types": [
        "label"
      ],
      "value": "Державний науково-дослідний контрольний інститут ветеринарних препаратів та кормових добавок."
    }
  ],
  "relationships": [],
  "status": "active",
  "types": [
    "facility"
  ]
}