{
  "admin": {
    "created": {
      "date": "2018-11-14",
      "schema_version": "1.0"
    },
    "last_modified": {
      "date": "2024-10-31",
      "schema_version": "2.0"
    }
  },
  "domains": [],
  "established": 2010,
  "external_ids": [
    {
      "all": [
        "grid.462293.8"
      ],
      "preferred": "grid.462293.8",
      "type": "grid"
    },
    {
      "all": [
        "0000 0004 0522 0627"
      ],
      "preferred": null,
      "type": "isni"
    }
  ],
  "id": "https://ror.org/0471cyx86",
  "links": [
    {
      "type": "website",
      "value": "https://www.micalis.fr"
    }
  ],
  "locations": [
    {
      "geonames_details": {
        "country_code": "FR",
        "country_name": "France",
        "lat": 48.69572,
        "lng": 2.18727,
        "name": "Orsay"
      },
      "geonames_id": 2989204
    },
    {
      "geonames_details": {
        "country_code": "FR",
        "country_name": "France",
        "lat": 48.75909,
        "lng": 2.16966,
        "name": "Jouy-en-Josas"
      },
      "geonames_id": 3012165
    }
  ],
  "names": [
    {
      "lang": "fr",
      "types": [
        "alias"
      ],
      "value": "Institut Micalis"
    },
    {
      "lang": "fr",
      "types": [
        "acronym"
      ],
      "value": "MICALIS"
    },
    {
      "lang": "en",
      "types": [
        "alias"
      ],
      "value": "Micalis Institute"
    },
    {
      "lang": "fr",
      "types": [
        "label",
        "ror_display"
      ],
      "value": "Microbiologie de l’alimentation au service de la santé"
    }
  ],
  "relationships": [
    {
      "label": "AgroParisTech",
      "type": "parent",
      "id": "https://ror.org/02kbmgc12"
    },
    {
      "label": "Centre Île-de-France - Jouy-en-Josas - Antony",
      "type": "parent",
      "id": "https://ror.org/00gtg0p11"
    },
    {
      "label": "Université Paris-Saclay",
      "type": "parent",
      "id": "https://ror.org/03xjwb503"
    }
  ],
  "status": "active",
  "types": [
    "facility"
  ]
}