{
  "admin": {
    "created": {
      "date": "2018-11-14",
      "schema_version": "1.0"
    },
    "last_modified": {
      "date": "2025-10-28",
      "schema_version": "2.1"
    }
  },
  "domains": [
    "inesc.pt"
  ],
  "established": 1980,
  "external_ids": [
    {
      "all": [
        "grid.464690.9"
      ],
      "preferred": "grid.464690.9",
      "type": "grid"
    },
    {
      "all": [
        "0000 0001 0754 4834"
      ],
      "preferred": null,
      "type": "isni"
    }
  ],
  "id": "https://ror.org/033wn8m60",
  "links": [
    {
      "type": "website",
      "value": "https://inesc.pt"
    }
  ],
  "locations": [
    {
      "geonames_details": {
        "continent_code": "EU",
        "continent_name": "Europe",
        "country_code": "PT",
        "country_name": "Portugal",
        "country_subdivision_code": "11",
        "country_subdivision_name": "Lisbon",
        "lat": 38.72509,
        "lng": -9.1498,
        "name": "Lisbon"
      },
      "geonames_id": 2267057
    }
  ],
  "names": [
    {
      "lang": null,
      "types": [
        "acronym"
      ],
      "value": "INESC"
    },
    {
      "lang": "en",
      "types": [
        "ror_display",
        "label"
      ],
      "value": "Institute for Systems Engineering and Computers"
    },
    {
      "lang": "pt",
      "types": [
        "label"
      ],
      "value": "Instituto de Engenharia de Sistemas e Computadores"
    }
  ],
  "relationships": [
    {
      "label": "INESC TEC",
      "type": "child",
      "id": "https://ror.org/05fa8ka61"
    },
    {
      "label": "Instituto de Engenharia de Sistemas e Computadores Investigação e Desenvolvimento",
      "type": "child",
      "id": "https://ror.org/04mqy3p58"
    },
    {
      "label": "Instituto de Engenharia de Sistemas e Computadores Microsistemas e Nanotecnologias",
      "type": "child",
      "id": "https://ror.org/022mzwp71"
    },
    {
      "label": "Instituto de Novas Tecnologias",
      "type": "child",
      "id": "https://ror.org/00we1pa83"
    }
  ],
  "status": "active",
  "types": [
    "nonprofit"
  ]
}