{
    "id": "https://ror.org/019wbnq12",
    "name": "Ramakrishna Mission Vidyamandira",
    "email_address": null,
    "ip_addresses": [],
    "established": 1898,
    "types": [
        "Other"
    ],
    "relationships": [],
    "addresses": [
        {
            "lat": 22.57688,
            "lng": 88.31857,
            "state": null,
            "state_code": null,
            "city": "Howrah",
            "geonames_city": {
                "id": 1270396,
                "city": "Howrah",
                "geonames_admin1": {
                    "name": "West Bengal",
                    "id": 1252881,
                    "ascii_name": "West Bengal",
                    "code": "IN.28"
                },
                "geonames_admin2": {
                    "name": "Howrah",
                    "id": 1270397,
                    "ascii_name": "Howrah",
                    "code": "IN.28.341"
                },
                "license": {
                    "attribution": "Data from geonames.org under a CC-BY 3.0 license",
                    "license": "http://creativecommons.org/licenses/by/3.0/"
                },
                "nuts_level1": {
                    "name": null,
                    "code": null
                },
                "nuts_level2": {
                    "name": null,
                    "code": null
                },
                "nuts_level3": {
                    "name": null,
                    "code": null
                }
            },
            "postcode": null,
            "primary": false,
            "line": null,
            "country_geonames_id": 1269750
        }
    ],
    "links": [
        "http://vidyamandira.ac.in/"
    ],
    "aliases": [],
    "acronyms": [],
    "status": "active",
    "wikipedia_url": "",
    "labels": [
        {
            "label": "রামকৃষ্ণ মিশন",
            "iso639": "bn"
        }
    ],
    "country": {
        "country_name": "India",
        "country_code": "IN"
    },
    "external_ids": {
        "ISNI": {
            "preferred": null,
            "all": [
                "0000 0001 1833 9764"
            ]
        },
        "Wikidata": {
            "preferred": "Q7288816",
            "all": [
                "Q7288816"
            ]
        },
        "GRID": {
            "preferred": "grid.465010.6",
            "all": "grid.465010.6"
        }
    }
}