{
  "admin": {
    "created": {
      "date": "2024-09-14",
      "schema_version": "2.0"
    },
    "last_modified": {
      "date": "2024-09-16",
      "schema_version": "2.0"
    }
  },
  "domains": [],
  "established": 2018,
  "external_ids": [
    {
      "all": [
        "Q109912164"
      ],
      "preferred": "Q109912164",
      "type": "wikidata"
    }
  ],
  "id": "https://ror.org/02a1v0072",
  "links": [
    {
      "type": "website",
      "value": "https://www.umitra.ac.id"
    }
  ],
  "locations": [
    {
      "geonames_details": {
        "country_code": "ID",
        "country_name": "Indonesia",
        "lat": -5.48888,
        "lng": 104.23617,
        "name": "Rajabasa"
      },
      "geonames_id": 1630208
    }
  ],
  "names": [
    {
      "lang": "id",
      "types": [
        "alias"
      ],
      "value": "Akademi Akuntansi Dan Manajemen Mitra Lampung"
    },
    {
      "lang": "en",
      "types": [
        "alias"
      ],
      "value": "Mitra University Indonesia"
    },
    {
      "lang": "id",
      "types": [
        "acronym"
      ],
      "value": "UMITRA"
    },
    {
      "lang": "id",
      "types": [
        "label",
        "ror_display"
      ],
      "value": "Universitas Mitra Indonesia"
    }
  ],
  "relationships": [],
  "status": "active",
  "types": [
    "education"
  ]
}