{
  "admin": {
    "created": {
      "date": "2018-11-14",
      "schema_version": "1.0"
    },
    "last_modified": {
      "date": "2025-01-22",
      "schema_version": "2.1"
    }
  },
  "domains": [
    "uniba.it"
  ],
  "established": 1925,
  "external_ids": [
    {
      "all": [
        "501100005362"
      ],
      "preferred": null,
      "type": "fundref"
    },
    {
      "all": [
        "grid.7644.1"
      ],
      "preferred": "grid.7644.1",
      "type": "grid"
    },
    {
      "all": [
        "0000 0001 0120 3326"
      ],
      "preferred": null,
      "type": "isni"
    },
    {
      "all": [
        "Q1236136"
      ],
      "preferred": null,
      "type": "wikidata"
    }
  ],
  "id": "https://ror.org/027ynra39",
  "links": [
    {
      "type": "website",
      "value": "https://www.uniba.it"
    },
    {
      "type": "wikipedia",
      "value": "http://en.wikipedia.org/wiki/University_of_Bari"
    }
  ],
  "locations": [
    {
      "geonames_details": {
        "continent_code": "EU",
        "continent_name": "Europe",
        "country_code": "IT",
        "country_name": "Italy",
        "country_subdivision_code": "75",
        "country_subdivision_name": "Apulia",
        "lat": 41.12066,
        "lng": 16.86982,
        "name": "Bari"
      },
      "geonames_id": 3182351
    }
  ],
  "names": [
    {
      "lang": "en",
      "types": [
        "alias"
      ],
      "value": "University of Bari"
    },
    {
      "lang": "en",
      "types": [
        "ror_display",
        "label"
      ],
      "value": "University of Bari Aldo Moro"
    },
    {
      "lang": "it",
      "types": [
        "label"
      ],
      "value": "Università degli Studi di Bari Aldo Moro"
    },
    {
      "lang": "fr",
      "types": [
        "label"
      ],
      "value": "Université de bari"
    }
  ],
  "relationships": [
    {
      "label": "Istituto Nazionale di Fisica Nucleare, Sezione di Bari",
      "type": "related",
      "id": "https://ror.org/022hq6c49"
    }
  ],
  "status": "active",
  "types": [
    "education",
    "funder"
  ]
}