{
  "admin": {
    "created": {
      "date": "2026-06-14",
      "schema_version": "2.1"
    },
    "last_modified": {
      "date": "2026-06-23",
      "schema_version": "2.1"
    }
  },
  "domains": [
    "hirschmann-stiftung.ch"
  ],
  "established": 1985,
  "external_ids": [
    {
      "all": [
        "501100011564"
      ],
      "preferred": "501100011564",
      "type": "fundref"
    }
  ],
  "id": "https://ror.org/03jytg320",
  "links": [
    {
      "type": "website",
      "value": "https://www.hirschmann-stiftung.ch"
    }
  ],
  "locations": [
    {
      "geonames_details": {
        "continent_code": "EU",
        "continent_name": "Europe",
        "country_code": "CH",
        "country_name": "Switzerland",
        "country_subdivision_code": "ZG",
        "country_subdivision_name": "Zug",
        "lat": 47.17242,
        "lng": 8.51745,
        "name": "Zug"
      },
      "geonames_id": 2657908
    }
  ],
  "names": [
    {
      "lang": "en",
      "types": [
        "label",
        "ror_display"
      ],
      "value": "Hirschmann Foundation"
    },
    {
      "lang": "de",
      "types": [
        "alias"
      ],
      "value": "Hirschmann Stiftung"
    },
    {
      "lang": "de",
      "types": [
        "label"
      ],
      "value": "Hirschmann-Stiftung"
    }
  ],
  "relationships": [],
  "status": "active",
  "types": [
    "funder",
    "nonprofit"
  ]
}