{
  "id": "https://ror.org/02cmd6814",
  "name": "Stroud Water Research Center",
  "email_address": null,
  "ip_addresses": [],
  "established": 1967,
  "types": [
    "Nonprofit"
  ],
  "relationships": [],
  "addresses": [
    {
      "lat": 39.82344,
      "lng": -75.78327,
      "state": null,
      "state_code": null,
      "city": "Avondale",
      "geonames_city": {
        "id": 4556349,
        "city": "Avondale",
        "geonames_admin1": {
          "name": "Pennsylvania",
          "id": 6254927,
          "ascii_name": "Pennsylvania",
          "code": "US.PA"
        },
        "geonames_admin2": {
          "name": "Chester",
          "id": 5184079,
          "ascii_name": "Chester",
          "code": "US.PA.029"
        },
        "license": {
          "attribution": "Data from geonames.org under a CC-BY 3.0 license",
          "license": "http://creativecommons.org/licenses/by/3.0/"
        },
        "nuts_level1": {
          "name": null,
          "code": null
        },
        "nuts_level2": {
          "name": null,
          "code": null
        },
        "nuts_level3": {
          "name": null,
          "code": null
        }
      },
      "postcode": null,
      "primary": false,
      "line": null,
      "country_geonames_id": 6252001
    }
  ],
  "links": [
    "http://www.stroudcenter.org/"
  ],
  "aliases": [],
  "acronyms": [],
  "status": "active",
  "wikipedia_url": "",
  "labels": [],
  "country": {
    "country_name": "United States",
    "country_code": "US"
  },
  "external_ids": {
    "ISNI": {
      "preferred": null,
      "all": [
        "0000 0000 9615 2850"
      ]
    },
    "Wikidata": {
      "preferred": null,
      "all": [
        "Q30279662"
      ]
    },
    "GRID": {
      "preferred": "grid.274177.0",
      "all": "grid.274177.0"
    },
    "FundRef": {
      "preferred": "100020393",
      "all": [
        "100020393"
      ]
    }
  }
}