{
  "admin": {
    "created": {
      "date": "2025-06-24",
      "schema_version": "2.1"
    },
    "last_modified": {
      "date": "2025-06-24",
      "schema_version": "2.1"
    }
  },
  "domains": [
    "acorn.org.au"
  ],
  "established": 1977,
  "external_ids": [
    {
      "all": [
        "501100022920"
      ],
      "preferred": "501100022920",
      "type": "fundref"
    }
  ],
  "id": "https://ror.org/00r80yr56",
  "links": [
    {
      "type": "website",
      "value": "https://www.acorn.org.au"
    }
  ],
  "locations": [
    {
      "geonames_details": {
        "continent_code": "OC",
        "continent_name": "Oceania",
        "country_code": "AU",
        "country_name": "Australia",
        "country_subdivision_code": "SA",
        "country_subdivision_name": "South Australia",
        "lat": -34.92866,
        "lng": 138.59863,
        "name": "Adelaide"
      },
      "geonames_id": 2078025
    }
  ],
  "names": [
    {
      "lang": "en",
      "types": [
        "acronym"
      ],
      "value": "ACORN"
    },
    {
      "lang": "en",
      "types": [
        "label",
        "ror_display"
      ],
      "value": "Australian College of Perioperative Nurses"
    },
    {
      "lang": "en",
      "types": [
        "alias"
      ],
      "value": "Australian Confederation of Operating Room Nurses"
    }
  ],
  "relationships": [],
  "status": "active",
  "types": [
    "funder"
  ]
}