{
  "admin": {
    "created": {
      "date": "2025-07-15",
      "schema_version": "2.1"
    },
    "last_modified": {
      "date": "2025-07-15",
      "schema_version": "2.1"
    }
  },
  "domains": [
    "kunmed.or.kr"
  ],
  "established": 1922,
  "external_ids": [
    {
      "all": [
        "0000 0005 0353 9295"
      ],
      "preferred": "0000 0005 0353 9295",
      "type": "isni"
    },
    {
      "all": [
        "Q16094889"
      ],
      "preferred": "Q16094889",
      "type": "wikidata"
    }
  ],
  "id": "https://ror.org/02jpv3e53",
  "links": [
    {
      "type": "website",
      "value": "https://www.kunmed.or.kr"
    },
    {
      "type": "wikipedia",
      "value": "https://ko.wikipedia.org/wiki/%EC%A0%84%EB%B6%81%ED%8A%B9%EB%B3%84%EC%9E%90%EC%B9%98%EB%8F%84_%EA%B5%B0%EC%82%B0%EC%9D%98%EB%A3%8C%EC%9B%90"
    }
  ],
  "locations": [
    {
      "geonames_details": {
        "continent_code": "AS",
        "continent_name": "Asia",
        "country_code": "KR",
        "country_name": "South Korea",
        "country_subdivision_code": "45",
        "country_subdivision_name": "Jeollabuk-do",
        "lat": 35.97861,
        "lng": 126.71139,
        "name": "Gunsan"
      },
      "geonames_id": 1842025
    }
  ],
  "names": [
    {
      "lang": "en",
      "types": [
        "label",
        "ror_display"
      ],
      "value": "Gunsan Medical Center"
    },
    {
      "lang": "ko",
      "types": [
        "label"
      ],
      "value": "군산의료원"
    },
    {
      "lang": "ko",
      "types": [
        "alias"
      ],
      "value": "전라북도 군산의료원"
    },
    {
      "lang": "ko",
      "types": [
        "alias"
      ],
      "value": "전북특별자치도 군산의료원"
    }
  ],
  "relationships": [],
  "status": "active",
  "types": [
    "healthcare"
  ]
}