{
  "admin": {
    "created": {
      "date": "2024-08-19",
      "schema_version": "2.0"
    },
    "last_modified": {
      "date": "2024-08-21",
      "schema_version": "2.0"
    }
  },
  "domains": [
    "eubd.edu.ba"
  ],
  "established": 2011,
  "external_ids": [],
  "id": "https://ror.org/02bw9cj21",
  "links": [
    {
      "type": "website",
      "value": "https://eubd.edu.ba"
    }
  ],
  "locations": [
    {
      "geonames_details": {
        "country_code": "BA",
        "country_name": "Bosnia and Herzegovina",
        "lat": 44.86995,
        "lng": 18.81012,
        "name": "Brčko"
      },
      "geonames_id": 3203521
    }
  ],
  "names": [
    {
      "lang": "bs",
      "types": [
        "acronym"
      ],
      "value": "EUBD"
    },
    {
      "lang": "en",
      "types": [
        "alias"
      ],
      "value": "European University Brcko District"
    },
    {
      "lang": "bs",
      "types": [
        "label",
        "ror_display"
      ],
      "value": "Evropski univerzitet Brčko distrikt"
    }
  ],
  "relationships": [],
  "status": "active",
  "types": [
    "education"
  ]
}